README.rst
setup.py
xinge_push/__init__.py
xinge_push/constant.py
xinge_push/message.py
xinge_push/schedule.py
xinge_push/style.py
xinge_push/xinge.py
xinge_push.egg-info/PKG-INFO
xinge_push.egg-info/SOURCES.txt
xinge_push.egg-info/dependency_links.txt
xinge_push.egg-info/top_level.txt
xinge_push.egg-info/zip-safe